receiver.v
module receiver(
    input clk, rst, rx, rx_enb,  //rx is the serial input, rx_enb is the enable signal from the baud rate generator
	output reg[7:0] data_out, // the final parallel output after receiving the 8 bits of data
	output reg rdy // ready signal (indicates thata data is ready when rdy=1)
    );
	
    localparam idle_state = 2'b00;
	localparam start_state = 2'b01;
    localparam data_state = 2'b10;
	localparam stop_state = 2'b11;

	reg [1:0] state = idle_state; // current state of the receiver FSM
	reg [2:0] index; // index to keep track of which bit of the data is being received (0 to 7)
	reg [7:0] data; // register to hold the data being received
	reg [3:0] tick_count; // counts from 0 o 15 to keep track of the baud rate ticks (16 ticks per bit)

	always@(posedge clk) begin 
		if (rst) begin 
			state <= idle_state;
			data_out <= 0;
			index <= 0;
			tick_count <= 0;
			rdy <= 0;
			data <= 0;
		end else begin 
			rdy <= 0;

			if(rx_enb) begin 
				case (state) 
				idle_state: begin 
                    if (rx == 0) begin // start bit detected
						state <= start_state;
						tick_count <= 0;
					end else begin 
						state <= idle_state;
					end
				end
				
				start_state: begin 
                        if (tick_count == 4'd7) begin // middle of the start bit
                            if (rx == 1'b0) begin // confirm start bit is still low
                                state <= data_state;
                                tick_count <= 4'b0;
                                index <= 3'b0;
                            end else begin 
                                state <= idle_state; // false start bit, go back to idle
                            end 
                        end else begin 
                            tick_count <= tick_count + 1'b1;
                        end
                end

				data_state: begin 
					if (tick_count == 4'd15) begin // end of the current data bit
						data[index] <= rx; // sample the data bit
						if (index == 3'h7) begin // last data bit received
							state <= stop_state;
						end else begin 
							index <= index + 1;
						end
						tick_count <= 0;
					end else begin 
						tick_count <= tick_count + 1;
					end
				end

				stop_state: begin 
					if (tick_count == 4'd15) begin // end of the stop bit
						if (rx == 1) begin // confirm stop bit is high
							data_out <= data; // output the received data
							rdy <= 1; // indicate data is ready
						end 
						state <= idle_state; 
					end else begin 
						tick_count <= tick_count + 1;
					end
				end

				endcase
			end
		end
	end
	
endmodule

transmitter.v
module transmitter(
    input clk, wr_enb, enb, rst, // clk is the system clock, wr_enb is the write enable signal to start transmission, enb is the enable signal from the baud rate generator, rst is the reset signal
    input [7:0] data_in, // the 8-bit parallel data input to be transmitted
    output reg tx , // the serial output (tx=0 for start bit, tx=data bits, tx=1 for stop bit)
    output busy // indicates that the transmitter is busy transmitting data (busy=1 when transmitting, busy=0 when idle
    );

    localparam idle_state = 2'b00;
    localparam start_state = 2'b01;
    localparam data_state = 2'b10;
    localparam stop_state = 2'b11;

    reg [7:0] data; // register to hold the data being transmitted
    reg [2:0] index; // index to keep track of which bit of the data is being transmitted (0 to 7)
    reg [1:0] state = idle_state;
        
    always@(posedge clk)
        begin
            if (rst) begin
                state <= idle_state;
                tx <= 1'b1;
                index <= 3'h0;
            end 
            else begin 

            case(state)

            idle_state: begin
                tx <= 1'b1; // idle state, tx is high
                if(wr_enb) begin
                    state <= start_state;
                    data <= data_in;
                    index <= 3'b000;
                end else begin
                    state <= idle_state;
                end
            end

            start_state: begin
                if(enb) begin
                    tx <= 1'b0;
                    state <= data_state;
                end else begin
                    state <= start_state;
                end
            end

            data_state: begin
                if(enb) begin
                    tx <= data[index]; // transmit the current data bit

                    if (index == 3'h7) begin
                    state <= stop_state;
                    end else begin
                    index <= index + 1'b1;
                    end
                end
            end

            stop_state:
            begin
                if(enb)
                begin
                    tx <= 1'b1; // transmit the stop bit (high)
                    state <= idle_state;
                end
            end

            default: begin
            tx <= 1'b1;
            state <= idle_state;
            end
            
            endcase
            end
        end

    

    assign busy = (state != idle_state) ; // the transmitter is busy when it is in any state other than idle
endmodule

baud_rate_generator.v
module baud_rate_generator(
    input clk, 
    output rx_enb, tx_enb
    );

    reg [12:0] tx_counter; // counts from 0 to 5207 to generate a tick every 5208 clock cycles (for 9600 baud rate with a 50 MHz clock)
    reg [9:0] rx_counter; // counts from 0 to 324 to generate a tick every 325 clock cycles (for 16 times the baud rate, which is 9600*16=153600 baud, with a 50 MHz clock)
    
    initial begin
        tx_counter = 13'b0;
        rx_counter = 10'b0;
    end

    // Transmitter Clock Divider (Standard Baud Rate)
    always @(posedge clk ) 
        begin
            if (tx_counter == 13'd5208) 
                tx_counter <= 0;
            else
                tx_counter <= tx_counter + 1'b1;
        end

    // Receiver Clock Divider (16x Baud Rate)
    always @(posedge clk ) 
        begin
            if (rx_counter == 10'd325) 
                rx_counter <= 0;
            else
                rx_counter <= rx_counter + 1'b1;
        end

    // Generate a 1-clock-cycle pulse when the counters hit 0
    assign tx_enb = (tx_counter == 0);
    assign rx_enb = (rx_counter == 0);

endmodule

uart_system.v
module uart_system(
    input clk, rst, wr_enb, rx_pin,
    input [7:0] data_in,
    output tx_pin, rdy,
    output [7:0] data_out   
    );

    wire tx_tick;
    wire rx_tick;

    baud_rate_generator baud_gen_inst (
        .clk(clk),
        .rx_enb(rx_tick),
        .tx_enb(tx_tick)
    );
    
    transmitter tx_inst (
        .clk(clk),
        .wr_enb(wr_enb),
        .rst(rst),
        .data_in(data_in),
        .tx(tx_pin),
        .enb(tx_tick)
    );

    receiver rx_inst (
        .clk(clk),
        .rst(rst),
        .rx(rx_pin),
        .rx_enb(rx_tick),
        .data_out(data_out),
        .rdy(rdy)
    );

endmodule

tb_uart_system.v
`timescale 1ns / 1ps

module tb_uart_system();

    // 1. Declare virtual wires and registers to plug into our system
    reg clk;
    reg rst;
    reg wr_enb;
    reg [7:0] data_in;
    
    wire tx_pin;
    wire rdy;
    wire [7:0] data_out;
    
    // The Loopback: We use the tx_pin wire as the input for rx_pin!
    wire rx_pin = tx_pin; 

    // 2. Instantiate the system we just built (The "Device Under Test")
    uart_system uut (
        .clk(clk),
        .rst(rst),
        .wr_enb(wr_enb),
        .rx_pin(rx_pin),
        .data_in(data_in),
        .tx_pin(tx_pin),
        .rdy(rdy),
        .data_out(data_out)
    );

    // 3. Generate a fake Clock (toggles every 5 nanoseconds)
    always #5 clk = ~clk;

    // 4. The Test Sequence (The script of what to do)
    initial begin
        // Tell the simulator to record the waveforms so we can see them
        $dumpfile("uart_waves.vcd");
        $dumpvars(0, tb_uart_system);

        // --- STEP 1: Initialization ---
        clk = 0;
        rst = 1;         // Hold the reset button down
        wr_enb = 0;
        data_in = 8'b0;
        
        #100;            // Wait for 100 nanoseconds
        rst = 0;         // Let go of the reset button
        #100;
        
        // --- STEP 2: Send a Message ---
        // Let's send the binary pattern 10100101 (Hex: A5)
        data_in = 8'b10100101; 
        
        // Pulse the write enable flag for exactly one clock cycle
        wr_enb = 1;
        #10; 
        wr_enb = 0;
        
        // --- STEP 3: Wait and Verify ---
        // Now we wait for the receiver's 'rdy' flag to pop up!
        // Because UART is slow, this will take tens of thousands of clock cycles.
        wait(rdy == 1'b1);
        
        // Wait just a little bit longer so we can see the end of the waveform
        #1000;
        
        // Check if the received data matches what we sent
        if (data_out == 8'b10100101) begin
            $display("SUCCESS! The receiver caught the correct data: %b", data_out);
        end else begin
            $display("FAILED! The receiver caught: %b", data_out);
        end

        // End the simulation
        $finish;
    end

endmodule

uart_waves.vcd
$date
	Thu Mar 26 20:18:41 2026
$end
$version
	Icarus Verilog
$end
$timescale
	1ps
$end
$scope module tb_uart_system $end
$var wire 1 ! rx_pin $end
$var wire 1 " tx_pin $end
$var wire 1 # rdy $end
$var wire 8 $ data_out [7:0] $end
$var reg 1 % clk $end
$var reg 8 & data_in [7:0] $end
$var reg 1 ' rst $end
$var reg 1 ( wr_enb $end
$scope module uut $end
$var wire 1 % clk $end
$var wire 8 ) data_in [7:0] $end
$var wire 1 ' rst $end
$var wire 1 ! rx_pin $end
$var wire 1 ( wr_enb $end
$var wire 1 * tx_tick $end
$var wire 1 " tx_pin $end
$var wire 1 + rx_tick $end
$var wire 1 # rdy $end
$var wire 8 , data_out [7:0] $end
$scope module baud_gen_inst $end
$var wire 1 % clk $end
$var wire 1 * tx_enb $end
$var wire 1 + rx_enb $end
$var reg 10 - rx_counter [9:0] $end
$var reg 13 . tx_counter [12:0] $end
$upscope $end
$scope module rx_inst $end
$var wire 1 % clk $end
$var wire 1 ' rst $end
$var wire 1 ! rx $end
$var wire 1 + rx_enb $end
$var parameter 2 / data_state $end
$var parameter 2 0 idle_state $end
$var parameter 2 1 start_state $end
$var parameter 2 2 stop_state $end
$var reg 8 3 data [7:0] $end
$var reg 8 4 data_out [7:0] $end
$var reg 3 5 index [2:0] $end
$var reg 1 # rdy $end
$var reg 2 6 state [1:0] $end
$var reg 4 7 tick_count [3:0] $end
$upscope $end
$scope module tx_inst $end
$var wire 1 % clk $end
$var wire 8 8 data_in [7:0] $end
$var wire 1 * enb $end
$var wire 1 ' rst $end
$var wire 1 ( wr_enb $end
$var wire 1 9 busy $end
$var parameter 2 : data_state $end
$var parameter 2 ; idle_state $end
$var parameter 2 < start_state $end
$var parameter 2 = stop_state $end
$var reg 8 > data [7:0] $end
$var reg 3 ? index [2:0] $end
$var reg 2 @ state [1:0] $end
$var reg 1 " tx $end
$upscope $end
$upscope $end
$upscope $end
$enddefinitions $end
$comment Show the parameter values. $end
$dumpall
b11 =
b1 <
b0 ;
b10 :
b11 2
b1 1
b0 0
b10 /
$end
#0
$dumpvars
b0 @
bx ?
bx >
09
b0 8
bx 7
b0 6
bx 5
bx 4
bx 3
b0 .
b0 -
bx ,
1+
1*
b0 )
0(
1'
b0 &
0%
bx $
x#
x"
x!
$end
#5000
0*
b1 .
0+
b1 -
b0 ?
1!
1"
b0 3
0#
b0 7
b0 5
b0 $
b0 ,
b0 4
1%
#10000
0%
#15000
b10 -
b10 .
1%
#20000
0%
#25000
b11 .
b11 -
1%
#30000
0%
#35000
b100 -
b100 .
1%
#40000
0%
#45000
b101 .
b101 -
1%
#50000
0%
#55000
b110 -
b110 .
1%
#60000
0%
#65000
b111 .
b111 -
1%
#70000
0%
#75000
b1000 -
b1000 .
1%
#80000
0%
#85000
b1001 .
b1001 -
1%
#90000
0%
#95000
b1010 -
b1010 .
1%
#100000
0%
0'
#105000
b1011 .
b1011 -
1%
#110000
0%
#115000
b1100 -
b1100 .
1%
#120000
0%
#125000
b1101 .
b1101 -
1%
#130000
0%
#135000
b1110 -
b1110 .
1%
#140000
0%
#145000
b1111 .
b1111 -
1%
#150000
0%
#155000
b10000 -
b10000 .
1%
#160000
0%
#165000
b10001 .
b10001 -
1%
#170000
0%
#175000
b10010 -
b10010 .
1%
#180000
0%
#185000
b10011 .
b10011 -
1%
#190000
0%
#195000
b10100 -
b10100 .
1%
#200000
0%
1(
b10100101 &
b10100101 )
b10100101 8
#205000
b10101 .
b10101 -
b10100101 >
19
b1 @
1%
#210000
0%
0(
#215000
b10110 -
b10110 .
1%
#220000
0%
#225000
b10111 .
b10111 -
1%
#230000
0%
#235000
b11000 -
b11000 .
1%
#240000
0%
#245000
b11001 .
b11001 -
1%
#250000
0%
#255000
b11010 -
b11010 .
1%
#260000
0%
#265000
b11011 .
b11011 -
1%
#270000
0%
#275000
b11100 -
b11100 .
1%
#280000
0%
#285000
b11101 .
b11101 -
1%
#290000
0%
#295000
b11110 -
b11110 .
1%
#300000
0%
#305000
b11111 .
b11111 -
1%
#310000
0%
#315000
b100000 -
b100000 .
1%
#320000
0%
#325000
b100001 .
b100001 -
1%
#330000
0%
#335000
b100010 -
b100010 .
1%
#340000
0%
#345000
b100011 .
b100011 -
1%
#350000
0%
#355000
b100100 -
b100100 .
1%
#360000
0%
#365000
b100101 .
b100101 -
1%
#370000
0%
#375000
b100110 -
b100110 .
1%
#380000
0%
#385000
b100111 .
b100111 -
1%
#390000
0%
#395000
b101000 -
b101000 .
1%
#400000
0%
#405000
b101001 .
b101001 -
1%
#410000
0%
#415000
b101010 -
b101010 .
1%
#420000
0%
#425000
b101011 .
b101011 -
1%
#430000
0%
#435000
b101100 -
b101100 .
1%
#440000
0%
#445000
b101101 .
b101101 -
1%
#450000
0%
#455000
b101110 -
b101110 .
1%
#460000
0%
#465000
b101111 .
b101111 -
1%
#470000
0%
#475000
b110000 -
b110000 .
1%
#480000
0%
#485000
b110001 .
b110001 -
1%
#490000
0%
#495000
b110010 -
b110010 .
1%
#500000
0%
#505000
b110011 .
b110011 -
1%
#510000
0%
#515000
b110100 -
b110100 .
1%
#520000
0%
#525000
b110101 .
b110101 -
1%
#530000
0%
#535000
b110110 -
b110110 .
1%
#540000
0%
#545000
b110111 .
b110111 -
1%
#550000
0%
#555000
b111000 -
b111000 .
1%
#560000
0%
#565000
b111001 .
b111001 -
1%
#570000
0%
#575000
b111010 -
b111010 .
1%
#580000
0%
#585000
b111011 .
b111011 -
1%
#590000
0%
#595000
b111100 -
b111100 .
1%
#600000
0%
#605000
b111101 .
b111101 -
1%
#610000
0%
#615000
b111110 -
b111110 .
1%
#620000
0%
#625000
b111111 .
b111111 -
1%
#630000
0%
#635000
b1000000 -
b1000000 .
1%
#640000
0%
#645000
b1000001 .
b1000001 -
1%
#650000
0%
#655000
b1000010 -
b1000010 .
1%
#660000
0%
#665000
b1000011 .
b1000011 -
1%
#670000
0%
#675000
b1000100 -
b1000100 .
1%
#680000
0%
#685000
b1000101 .
b1000101 -
1%
#690000
0%
#695000
b1000110 -
b1000110 .
1%
#700000
0%
#705000
b1000111 .
b1000111 -
1%
#710000
0%
#715000
b1001000 -
b1001000 .
1%
#720000
0%
#725000
b1001001 .
b1001001 -
1%
#730000
0%
#735000
b1001010 -
b1001010 .
1%
#740000
0%
#745000
b1001011 .
b1001011 -
1%
#750000
0%
#755000
b1001100 -
b1001100 .
1%
#760000
0%
#765000
b1001101 .
b1001101 -
1%
#770000
0%
#775000
b1001110 -
b1001110 .
1%
#780000
0%
#785000
b1001111 .
b1001111 -
1%
#790000
0%
#795000
b1010000 -
b1010000 .
1%
#800000
0%
#805000
b1010001 .
b1010001 -
1%
#810000
0%
#815000
b1010010 -
b1010010 .
1%
#820000
0%
#825000
b1010011 .
b1010011 -
1%
#830000
0%
#835000
b1010100 -
b1010100 .
1%
#840000
0%
#845000
b1010101 .
b1010101 -
1%
#850000
0%
#855000
b1010110 -
b1010110 .
1%
#860000
0%
#865000
b1010111 .
b1010111 -
1%
#870000
0%
#875000
b1011000 -
b1011000 .
1%
#880000
0%
#885000
b1011001 .
b1011001 -
1%
#890000
0%
#895000
b1011010 -
b1011010 .
1%
#900000
0%
#905000
b1011011 .
b1011011 -
1%
#910000
0%
#915000
b1011100 -
b1011100 .
1%
#920000
0%
#925000
b1011101 .
b1011101 -
1%
#930000
0%
#935000
b1011110 -
b1011110 .
1%
#940000
0%
#945000
b1011111 .
b1011111 -
1%
#950000
0%
#955000
b1100000 -
b1100000 .
1%
#960000
0%
#965000
b1100001 .
b1100001 -
1%
#970000
0%
#975000
b1100010 -
b1100010 .
1%
#980000
0%
#985000
b1100011 .
b1100011 -
1%
#990000
0%
#995000
b1100100 -
b1100100 .
1%
#1000000
0%
#1005000
b1100101 .
b1100101 -
1%
#1010000
0%
#1015000
b1100110 -
b1100110 .
1%
#1020000
0%
#1025000
b1100111 .
b1100111 -
1%
#1030000
0%
#1035000
b1101000 -
b1101000 .
1%
#1040000
0%
#1045000
b1101001 .
b1101001 -
1%
#1050000
0%
#1055000
b1101010 -
b1101010 .
1%
#1060000
0%
#1065000
b1101011 .
b1101011 -
1%
#1070000
0%
#1075000
b1101100 -
b1101100 .
1%
#1080000
0%
#1085000
b1101101 .
b1101101 -
1%
#1090000
0%
#1095000
b1101110 -
b1101110 .
1%
#1100000
0%
#1105000
b1101111 .
b1101111 -
1%
#1110000
0%
#1115000
b1110000 -
b1110000 .
1%
#1120000
0%
#1125000
b1110001 .
b1110001 -
1%
#1130000
0%
#1135000
b1110010 -
b1110010 .
1%
#1140000
0%
#1145000
b1110011 .
b1110011 -
1%
#1150000
0%
#1155000
b1110100 -
b1110100 .
1%
#1160000
0%
#1165000
b1110101 .
b1110101 -
1%
#1170000
0%
#1175000
b1110110 -
b1110110 .
1%
#1180000
0%
#1185000
b1110111 .
b1110111 -
1%
#1190000
0%
#1195000
b1111000 -
b1111000 .
1%
#1200000
0%
#1205000
b1111001 .
b1111001 -
1%
#1210000
0%
#1215000
b1111010 -
b1111010 .
1%
#1220000
0%
#1225000
b1111011 .
b1111011 -
1%
#1230000
0%
#1235000
b1111100 -
b1111100 .
1%
#1240000
0%
#1245000
b1111101 .
b1111101 -
1%
#1250000
0%
#1255000
b1111110 -
b1111110 .
1%
#1260000
0%
#1265000
b1111111 .
b1111111 -
1%
#1270000
0%
#1275000
b10000000 -
b10000000 .
1%
#1280000
0%
#1285000
b10000001 .
b10000001 -
1%
#1290000
0%
#1295000
b10000010 -
b10000010 .
1%
#1300000
0%
#1305000
b10000011 .
b10000011 -
1%
#1310000
0%
#1315000
b10000100 -
b10000100 .
1%
#1320000
0%
#1325000
b10000101 .
b10000101 -
1%
#1330000
0%
#1335000
b10000110 -
b10000110 .
1%
#1340000
0%
#1345000
b10000111 .
b10000111 -
1%
#1350000
0%
#1355000
b10001000 -
b10001000 .
1%
#1360000
0%
#1365000
b10001001 .
b10001001 -
1%
#1370000
0%
#1375000
b10001010 -
b10001010 .
1%
#1380000
0%
#1385000
b10001011 .
b10001011 -
1%
#1390000
0%
#1395000
b10001100 -
b10001100 .
1%
#1400000
0%
#1405000
b10001101 .
b10001101 -
1%
#1410000
0%
#1415000
b10001110 -
b10001110 .
1%
#1420000
0%
#1425000
b10001111 .
b10001111 -
1%
#1430000
0%
#1435000
b10010000 -
b10010000 .
1%
#1440000
0%
#1445000
b10010001 .
b10010001 -
1%
#1450000
0%
#1455000
b10010010 -
b10010010 .
1%
#1460000
0%
#1465000
b10010011 .
b10010011 -
1%
#1470000
0%
#1475000
b10010100 -
b10010100 .
1%
#1480000
0%
#1485000
b10010101 .
b10010101 -
1%
#1490000
0%
#1495000
b10010110 -
b10010110 .
1%
#1500000
0%
#1505000
b10010111 .
b10010111 -
1%
#1510000
0%
#1515000
b10011000 -
b10011000 .
1%
#1520000
0%
#1525000
b10011001 .
b10011001 -
1%
#1530000
0%
#1535000
b10011010 -
b10011010 .
1%
#1540000
0%
#1545000
b10011011 .
b10011011 -
1%
#1550000
0%
#1555000
b10011100 -
b10011100 .
1%
#1560000
0%
#1565000
b10011101 .
b10011101 -
1%
#1570000
0%
#1575000
b10011110 -
b10011110 .
1%
#1580000
0%
#1585000
b10011111 .
b10011111 -
1%
#1590000
0%
#1595000
b10100000 -
b10100000 .
1%
#1600000
0%
#1605000
b10100001 .
b10100001 -
1%
#1610000
0%
#1615000
b10100010 -
b10100010 .
1%
#1620000
0%
#1625000
b10100011 .
b10100011 -
1%
#1630000
0%
#1635000
b10100100 -
b10100100 .
1%
#1640000
0%
#1645000
b10100101 .
b10100101 -
1%
#1650000
0%
#1655000
b10100110 -
b10100110 .
1%
#1660000
0%
#1665000
b10100111 .
b10100111 -
1%
#1670000
0%
#1675000
b10101000 -
b10101000 .
1%
#1680000
0%
#1685000
b10101001 .
b10101001 -
1%
#1690000
0%
#1695000
b10101010 -
b10101010 .
1%
#1700000
0%
#1705000
b10101011 .
b10101011 -
1%
#1710000
0%
#1715000
b10101100 -
b10101100 .
1%
#1720000
0%
#1725000
b10101101 .
b10101101 -
1%
#1730000
0%
#1735000
b10101110 -
b10101110 .
1%
#1740000
0%
#1745000
b10101111 .
b10101111 -
1%
#1750000
0%
#1755000
b10110000 -
b10110000 .
1%
#1760000
0%
#1765000
b10110001 .
b10110001 -
1%
#1770000
0%
#1775000
b10110010 -
b10110010 .
1%
#1780000
0%
#1785000
b10110011 .
b10110011 -
1%
#1790000
0%
#1795000
b10110100 -
b10110100 .
1%
#1800000
0%
#1805000
b10110101 .
b10110101 -
1%
#1810000
0%
#1815000
b10110110 -
b10110110 .
1%
#1820000
0%
#1825000
b10110111 .
b10110111 -
1%
#1830000
0%
#1835000
b10111000 -
b10111000 .
1%
#1840000
0%
#1845000
b10111001 .
b10111001 -
1%
#1850000
0%
#1855000
b10111010 -
b10111010 .
1%
#1860000
0%
#1865000
b10111011 .
b10111011 -
1%
#1870000
0%
#1875000
b10111100 -
b10111100 .
1%
#1880000
0%
#1885000
b10111101 .
b10111101 -
1%
#1890000
0%
#1895000
b10111110 -
b10111110 .
1%
#1900000
0%
#1905000
b10111111 .
b10111111 -
1%
#1910000
0%
#1915000
b11000000 -
b11000000 .
1%
#1920000
0%
#1925000
b11000001 .
b11000001 -
1%
#1930000
0%
#1935000
b11000010 -
b11000010 .
1%
#1940000
0%
#1945000
b11000011 .
b11000011 -
1%
#1950000
0%
#1955000
b11000100 -
b11000100 .
1%
#1960000
0%
#1965000
b11000101 .
b11000101 -
1%
#1970000
0%
#1975000
b11000110 -
b11000110 .
1%
#1980000
0%
#1985000
b11000111 .
b11000111 -
1%
#1990000
0%
#1995000
b11001000 -
b11001000 .
1%
#2000000
0%
#2005000
b11001001 .
b11001001 -
1%
#2010000
0%
#2015000
b11001010 -
b11001010 .
1%
#2020000
0%
#2025000
b11001011 .
b11001011 -
1%
#2030000
0%
#2035000
b11001100 -
b11001100 .
1%
#2040000
0%
#2045000
b11001101 .
b11001101 -
1%
#2050000
0%
#2055000
b11001110 -
b11001110 .
1%
#2060000
0%
#2065000
b11001111 .
b11001111 -
1%
#2070000
0%
#2075000
b11010000 -
b11010000 .
1%
#2080000
0%
#2085000
b11010001 .
b11010001 -
1%
#2090000
0%
#2095000
b11010010 -
b11010010 .
1%
#2100000
0%
#2105000
b11010011 .
b11010011 -
1%
#2110000
0%
#2115000
b11010100 -
b11010100 .
1%
#2120000
0%
#2125000
b11010101 .
b11010101 -
1%
#2130000
0%
#2135000
b11010110 -
b11010110 .
1%
#2140000
0%
#2145000
b11010111 .
b11010111 -
1%
#2150000
0%
#2155000
b11011000 -
b11011000 .
1%
#2160000
0%
#2165000
b11011001 .
b11011001 -
1%
#2170000
0%
#2175000
b11011010 -
b11011010 .
1%
#2180000
0%
#2185000
b11011011 .
b11011011 -
1%
#2190000
0%
#2195000
b11011100 -
b11011100 .
1%
#2200000
0%
#2205000
b11011101 .
b11011101 -
1%
#2210000
0%
#2215000
b11011110 -
b11011110 .
1%
#2220000
0%
#2225000
b11011111 .
b11011111 -
1%
#2230000
0%
#2235000
b11100000 -
b11100000 .
1%
#2240000
0%
#2245000
b11100001 .
b11100001 -
1%
#2250000
0%
#2255000
b11100010 -
b11100010 .
1%
#2260000
0%
#2265000
b11100011 .
b11100011 -
1%
#2270000
0%
#2275000
b11100100 -
b11100100 .
1%
#2280000
0%
#2285000
b11100101 .
b11100101 -
1%
#2290000
0%
#2295000
b11100110 -
b11100110 .
1%
#2300000
0%
#2305000
b11100111 .
b11100111 -
1%
#2310000
0%
#2315000
b11101000 -
b11101000 .
1%
#2320000
0%
#2325000
b11101001 .
b11101001 -
1%
#2330000
0%
#2335000
b11101010 -
b11101010 .
1%
#2340000
0%
#2345000
b11101011 .
b11101011 -
1%
#2350000
0%
#2355000
b11101100 -
b11101100 .
1%
#2360000
0%
#2365000
b11101101 .
b11101101 -
1%
#2370000
0%
#2375000
b11101110 -
b11101110 .
1%
#2380000
0%
#2385000
b11101111 .
b11101111 -
1%
#2390000
0%
#2395000
b11110000 -
b11110000 .
1%
#2400000
0%
#2405000
b11110001 .
b11110001 -
1%
#2410000
0%
#2415000
b11110010 -
b11110010 .
1%
#2420000
0%
#2425000
b11110011 .
b11110011 -
1%
#2430000
0%
#2435000
b11110100 -
b11110100 .
1%
#2440000
0%
#2445000
b11110101 .
b11110101 -
1%
#2450000
0%
#2455000
b11110110 -
b11110110 .
1%
#2460000
0%
#2465000
b11110111 .
b11110111 -
1%
#2470000
0%
#2475000
b11111000 -
b11111000 .
1%
#2480000
0%
#2485000
b11111001 .
b11111001 -
1%
#2490000
0%
#2495000
b11111010 -
b11111010 .
1%
#2500000
0%
#2505000
b11111011 .
b11111011 -
1%
#2510000
0%
#2515000
b11111100 -
b11111100 .
1%
#2520000
0%
#2525000
b11111101 .
b11111101 -
1%
#2530000
0%
#2535000
b11111110 -
b11111110 .
1%
#2540000
0%
#2545000
b11111111 .
b11111111 -
1%
#2550000
0%
#2555000
b100000000 -
b100000000 .
1%
#2560000
0%
#2565000
b100000001 .
b100000001 -
1%
#2570000
0%
#2575000
b100000010 -
b100000010 .
1%
#2580000
0%
#2585000
b100000011 .
b100000011 -
1%
#2590000
0%
#2595000
b100000100 -
b100000100 .
1%
#2600000
0%
#2605000
b100000101 .
b100000101 -
1%
#2610000
0%
#2615000
b100000110 -
b100000110 .
1%
#2620000
0%
#2625000
b100000111 .
b100000111 -
1%
#2630000
0%
#2635000
b100001000 -
b100001000 .
1%
#2640000
0%
#2645000
b100001001 .
b100001001 -
1%
#2650000
0%
#2655000
b100001010 -
b100001010 .
1%
#2660000
0%
#2665000
b100001011 .
b100001011 -
1%
#2670000
0%
#2675000
b100001100 -
b100001100 .
1%
#2680000
0%
#2685000
b100001101 .
b100001101 -
1%
#2690000
0%
#2695000
b100001110 -
b100001110 .
1%
#2700000
0%
#2705000
b100001111 .
b100001111 -
1%
#2710000
0%
#2715000
b100010000 -
b100010000 .
1%
#2720000
0%
#2725000
b100010001 .
b100010001 -
1%
#2730000
0%
#2735000
b100010010 -
b100010010 .
1%
#2740000
0%
#2745000
b100010011 .
b100010011 -
1%
#2750000
0%
#2755000
b100010100 -
b100010100 .
1%
#2760000
0%
#2765000
b100010101 .
b100010101 -
1%
#2770000
0%
#2775000
b100010110 -
b100010110 .
1%
#2780000
0%
#2785000
b100010111 .
b100010111 -
1%
#2790000
0%
#2795000
b100011000 -
b100011000 .
1%
#2800000
0%
#2805000
b100011001 .
b100011001 -
1%
#2810000
0%
#2815000
b100011010 -
b100011010 .
1%
#2820000
0%
#2825000
b100011011 .
b100011011 -
1%
#2830000
0%
#2835000
b100011100 -
b100011100 .
1%
#2840000
0%
#2845000
b100011101 .
b100011101 -
1%
#2850000
0%
#2855000
b100011110 -
b100011110 .
1%
#2860000
0%
#2865000
b100011111 .
b100011111 -
1%
#2870000
0%
#2875000
b100100000 -
b100100000 .
1%
#2880000
0%
#2885000
b100100001 .
b100100001 -
1%
#2890000
0%
#2895000
b100100010 -
b100100010 .
1%
#2900000
0%
#2905000
b100100011 .
b100100011 -
1%
#2910000
0%
#2915000
b100100100 -
b100100100 .
1%
#2920000
0%
#2925000
b100100101 .
b100100101 -
1%
#2930000
0%
#2935000
b100100110 -
b100100110 .
1%
#2940000
0%
#2945000
b100100111 .
b100100111 -
1%
#2950000
0%
#2955000
b100101000 -
b100101000 .
1%
#2960000
0%
#2965000
b100101001 .
b100101001 -
1%
#2970000
0%
#2975000
b100101010 -
b100101010 .
1%
#2980000
0%
#2985000
b100101011 .
b100101011 -
1%
#2990000
0%
#2995000
b100101100 -
b100101100 .
1%
#3000000
0%
#3005000
b100101101 .
b100101101 -
1%
#3010000
0%
#3015000
b100101110 -
b100101110 .
1%
#3020000
0%
#3025000
b100101111 .
b100101111 -
1%
#3030000
0%
#3035000
b100110000 -
b100110000 .
1%
#3040000
0%
#3045000
b100110001 .
b100110001 -
1%
#3050000
0%
#3055000
b100110010 -
b100110010 .
1%
#3060000
0%
#3065000
b100110011 .
b100110011 -
1%
#3070000
0%
#3075000
b100110100 -
b100110100 .
1%
#3080000
0%
#3085000
b100110101 .
b100110101 -
1%
#3090000
0%
#3095000
b100110110 -
b100110110 .
1%
#3100000
0%
#3105000
b100110111 .
b100110111 -
1%
#3110000
0%
#3115000
b100111000 -
b100111000 .
1%
#3120000
0%
#3125000
b100111001 .
b100111001 -
1%
#3130000
0%
#3135000
b100111010 -
b100111010 .
1%
#3140000
0%
#3145000
b100111011 .
b100111011 -
1%
#3150000
0%
#3155000
b100111100 -
b100111100 .
1%
#3160000
0%
#3165000
b100111101 .
b100111101 -
1%
#3170000
0%
#3175000
b100111110 -
b100111110 .
1%
#3180000
0%
#3185000
b100111111 .
b100111111 -
1%
#3190000
0%
#3195000
b101000000 -
b101000000 .
1%
#3200000
0%
#3205000
b101000001 .
b101000001 -
1%
#3210000
0%
#3215000
b101000010 -
b101000010 .
1%
#3220000
0%
#3225000
b101000011 .
b101000011 -
1%
#3230000
0%
#3235000
b101000100 -
b101000100 .
1%
#3240000
0%
#3245000
b101000101 .
b101000101 -
1%
#3250000
0%
#3255000
1+
b0 -
b101000110 .
1%
#3260000
0%
#3265000
b101000111 .
0+
b1 -
1%
#3270000
0%
#3275000
b10 -
b101001000 .
1%
#3280000
0%
#3285000
b101001001 .
b11 -
1%
#3290000
0%
#3295000
b100 -
b101001010 .
1%
#3300000
0%
#3305000
b101001011 .
b101 -
1%
#3310000
0%
#3315000
b110 -
b101001100 .
1%
#3320000
0%
#3325000
b101001101 .
b111 -
1%
#3330000
0%
#3335000
b1000 -
b101001110 .
1%
#3340000
0%
#3345000
b101001111 .
b1001 -
1%
#3350000
0%
#3355000
b1010 -
b101010000 .
1%
#3360000
0%
#3365000
b101010001 .
b1011 -
1%
#3370000
0%
#3375000
b1100 -
b101010010 .
1%
#3380000
0%
#3385000
b101010011 .
b1101 -
1%
#3390000
0%
#3395000
b1110 -
b101010100 .
1%
#3400000
0%
#3405000
b101010101 .
b1111 -
1%
#3410000
0%
#3415000
b10000 -
b101010110 .
1%
#3420000
0%
#3425000
b101010111 .
b10001 -
1%
#3430000
0%
#3435000
b10010 -
b101011000 .
1%
#3440000
0%
#3445000
b101011001 .
b10011 -
1%
#3450000
0%
#3455000
b10100 -
b101011010 .
1%
#3460000
0%
#3465000
b101011011 .
b10101 -
1%
#3470000
0%
#3475000
b10110 -
b101011100 .
1%
#3480000
0%
#3485000
b101011101 .
b10111 -
1%
#3490000
0%
#3495000
b11000 -
b101011110 .
1%
#3500000
0%
#3505000
b101011111 .
b11001 -
1%
#3510000
0%
#3515000
b11010 -
b101100000 .
1%
#3520000
0%
